al360_nlp_feature_extractors/__init__.py
al360_nlp_feature_extractors/attribute_extractors.py
al360_nlp_feature_extractors/data/__init__.py
al360_nlp_feature_extractors/data/female-words.txt
al360_nlp_feature_extractors/data/male-words.txt
al360_nlp_feature_extractors/data/neutral-words.txt
al360_nlp_feature_extractors-0.1.0.dist-info/METADATA
al360_nlp_feature_extractors-0.1.0.dist-info/WHEEL
al360_nlp_feature_extractors-0.1.0.dist-info/top_level.txt
al360_nlp_feature_extractors-0.1.0.dist-info/RECORD
