Metadata-Version: 2.1
Name: al360_nlp_feature_extractors
Version: 0.1.0
Summary: NLP Feature Extractors
Home-page: https://github.com/affectlog360/al360-trustworthy-ai-widgets
Author: 
Author-email: al360_taiwidgets-maintain@affectlog.com
Classifier: Programming Language :: Python :: 3
Classifier: Programming Language :: Python :: 3.7
Classifier: Programming Language :: Python :: 3.8
Classifier: Programming Language :: Python :: 3.9
Classifier: License :: OSI Approved :: MIT License
Classifier: Operating System :: OS Independent
Classifier: Development Status :: 3 - Alpha
Requires-Dist: datasets
Requires-Dist: negspacy>=1.0.0
Requires-Dist: numpy>=1.17.2
Requires-Dist: sentencepiece
Requires-Dist: spacy
Requires-Dist: tqdm
Requires-Dist: al360-taiutils>=0.4.2
